{"background_url": "", "global_font_url": "https://fonts.googleapis.com/css2?family=Cairo:wght@200..1000&display=swap", "global_font_family": "'Cairo', sans-serif", "elements": {"p1_name": {"x": 477.71134020618507, "y": 948.8865979381444, "fontSize": "48px", "color": "#ffffff", "text": "Player 1", "visible": true}, "p1_score": {"x": 681, "y": 945, "fontSize": "64px", "color": "#ffd500", "text": "2", "visible": true}, "tournament_round": {"x": 899, "y": 964, "fontSize": "24px", "color": "#aaaaaa", "text": "Winners Semis", "visible": true}, "p2_name": {"x": 1520, "y": 950, "fontSize": "48px", "color": "#ffffff", "text": "Player 2", "visible": true}, "p2_score": {"x": 1120, "y": 950, "fontSize": "64px", "color": "#ffd500", "text": "0", "visible": true}, "p1_team": {"x": 471.25773195876275, "y": 898.8865979381443, "fontSize": "24px", "color": "#aaaaaa", "text": "[TEAM]", "visible": true}, "p2_team": {"x": 1520, "y": 900, "fontSize": "24px", "color": "#ffffff", "text": "[TEAM]", "visible": true}, "tournament_name": {"x": 904.9999999999999, "y": 925.7938144329897, "fontSize": "24px", "color": "#aaaaaa", "text": "My Awesome Tournament", "visible": true}, "p1_avatar": {"type": "image", "x": 196.55670103092783, "y": 893.4226804123712, "width": 180, "height": 180, "src": "/static/player_placeholder.svg", "visible": true}, "p2_avatar": {"type": "image", "x": 1730.123711340206, "y": 894.5360824742279, "width": 180, "height": 180, "src": "/static/player_placeholder.svg", "visible": true}, "p1_flag": {"type": "image", "x": 142.54639175257722, "y": 959.4536082474228, "width": 70, "height": 47, "src": "/static/flag_placeholder.svg", "visible": true}, "p2_flag": {"type": "image", "x": 1784.9484536082473, "y": 957.4742268041239, "width": 70, "height": 80, "src": "/static/flag_placeholder.svg", "visible": true}}}